dglke/VERSION.txt
dglke/__init__.py
dglke/convert.py
dglke/dist_train.py
dglke/eval.py
dglke/infer_emb_sim.py
dglke/infer_score.py
dglke/kvclient.py
dglke/kvserver.py
dglke/partition.py
dglke/train.py
dglke/train_mxnet.py
dglke/train_pytorch.py
dglke/utils.py
dglke/dataloader/KGDataset.py
dglke/dataloader/__init__.py
dglke/dataloader/sampler.py
dglke/models/__init__.py
dglke/models/general_models.py
dglke/models/infer.py
dglke/models/ke_model.py
dglke/models/mxnet/__init__.py
dglke/models/mxnet/score_fun.py
dglke/models/mxnet/tensor_models.py
dglke/models/pytorch/__init__.py
dglke/models/pytorch/ke_tensor.py
dglke/models/pytorch/score_fun.py
dglke/models/pytorch/tensor_models.py
dglke-0.1.2.dist-info/METADATA
dglke-0.1.2.dist-info/WHEEL
dglke-0.1.2.dist-info/entry_points.txt
dglke-0.1.2.dist-info/top_level.txt
dglke-0.1.2.dist-info/RECORD
